TelloMovement/__init__.py
TelloMovement-1.0.0.dist-info/METADATA
TelloMovement-1.0.0.dist-info/RECORD
TelloMovement-1.0.0.dist-info/WHEEL
TelloMovement-1.0.0.dist-info/top_level.txt
