Metadata-Version: 2.1
Name: TelloMovement
Version: 1.0.0
Summary: Library with all methods compatible with the Tello Drones SDK
Home-page: UNKNOWN
Author: Hudson Nobles
Author-email: UNKNOWN
License: LICENSE.txt
Platform: UNKNOWN
